mdsanima_dev/__init__.py
mdsanima_dev/_version.py
mdsanima_dev/colors.py
mdsanima_dev/emoji.py
mdsanima_dev/json/emoji-list.json
mdsanima_dev/json/emoji-modifiers.json
mdsanima_dev/utils/__init__.py
mdsanima_dev/utils/converts.py
mdsanima_dev/utils/table.py
mdsanima_dev/utils/tools.py
mdsanima_dev-0.2.0.dist-info/LICENSE
mdsanima_dev-0.2.0.dist-info/METADATA
mdsanima_dev-0.2.0.dist-info/WHEEL
mdsanima_dev-0.2.0.dist-info/entry_points.txt
mdsanima_dev-0.2.0.dist-info/top_level.txt
mdsanima_dev-0.2.0.dist-info/RECORD
