Metadata-Version: 2.1
Name: mdsanima_dev
Version: 0.2.0
Summary: MDSANIMA-DEV Python Development Tools
Author-email: Marcin Różewski <marcinrozewski@gmail.com>
License: MIT License
Project-URL: homepage, https://github.com/mdsanima-dev/mdsanima-dev
Project-URL: documentation, https://github.com/mdsanima-dev/mdsanima-dev#readme
Project-URL: repository, https://github.com/mdsanima-dev/mdsanima-dev.git
Project-URL: changelog, https://github.com/mdsanima-dev/mdsanima-dev/blob/main/CHANGELOG.md
Keywords: animation,automatic,bash,changelog,cli,colors,command-line,console-app,console-application,console,development,emoj,mdsanima-dev,mdsanima,python-library,python,python3,shell-script,shell,terminal,tools,versioning,vfx,zsh
Classifier: Development Status :: 5 - Production/Stable
Classifier: Environment :: Console
Classifier: Environment :: Plugins
Classifier: Intended Audience :: Developers
Classifier: Intended Audience :: Education
Classifier: Intended Audience :: End Users/Desktop
Classifier: Intended Audience :: Information Technology
Classifier: Intended Audience :: Legal Industry
Classifier: Intended Audience :: Other Audience
Classifier: Intended Audience :: System Administrators
Classifier: License :: OSI Approved :: MIT License
Classifier: Natural Language :: English
Classifier: Natural Language :: Polish
Classifier: Operating System :: MacOS
Classifier: Operating System :: Microsoft :: Windows
Classifier: Operating System :: POSIX :: BSD
Classifier: Operating System :: POSIX :: Linux
Classifier: Operating System :: Unix
Classifier: Programming Language :: Python :: 3.10
Classifier: Topic :: Desktop Environment
Classifier: Topic :: Documentation :: Sphinx
Classifier: Topic :: Education :: Testing
Classifier: Topic :: Home Automation
Classifier: Topic :: Scientific/Engineering :: Information Analysis
Classifier: Topic :: Software Development
Classifier: Topic :: Software Development :: Libraries
Classifier: Topic :: Software Development :: Libraries :: Python Modules
Classifier: Topic :: System
Classifier: Topic :: System :: Console Fonts
Classifier: Topic :: System :: Filesystems
Classifier: Topic :: System :: Logging
Classifier: Topic :: System :: Operating System
Classifier: Topic :: System :: Shells
Classifier: Topic :: System :: System Shells
Classifier: Topic :: System :: Systems Administration
Classifier: Topic :: System :: Systems Administration :: Authentication/Directory
Classifier: Topic :: Terminals
Classifier: Topic :: Text Processing
Classifier: Topic :: Text Processing :: Markup :: reStructuredText
Classifier: Topic :: Utilities
Classifier: Typing :: Typed
Requires-Python: >=3.10
License-File: LICENSE
